sashimono.py
sashimono-1.1.3.dist-info/licenses/LICENSE
sashimono-1.1.3.dist-info/METADATA
sashimono-1.1.3.dist-info/WHEEL
sashimono-1.1.3.dist-info/top_level.txt
sashimono-1.1.3.dist-info/RECORD
