Metadata-Version: 2.4
Name: sashimono
Version: 1.1.3
Summary: A lean dependency injection container
Author-email: Jesús Enrique Fuentes González <jesusefg12@gmail.com>
License: MIT License
Classifier: License :: OSI Approved :: MIT License
Requires-Python: >=3.12
License-File: LICENSE
Provides-Extra: dev
Requires-Dist: pytest-cov>=6.0.0; extra == "dev"
Requires-Dist: pytest>=8.3.4; extra == "dev"
Dynamic: license-file
